cooltables/__init__.py
cooltables/cooltables.py
cooltables/themes.py
cooltables-0.0.3.dist-info/LICENSE
cooltables-0.0.3.dist-info/METADATA
cooltables-0.0.3.dist-info/WHEEL
cooltables-0.0.3.dist-info/top_level.txt
cooltables-0.0.3.dist-info/RECORD
